{
  "$schema": "https://biomejs.dev/schemas/1.9.4/schema.json",
  "vcs": {
    "enabled": true,
    "clientKind": "git",
    "useIgnoreFile": true
  },
  "files": {
    "ignoreUnknown": true,
    "ignore": [
      "**/dist/**",
      "**/build/**",
      "**/.svelte-kit/**",
      "**/node_modules/**",
      "**/*.min.js",
      "dashboard/static/**"
    ]
  },
  "formatter": {
    "enabled": true,
    "indentStyle": "space",
    "indentWidth": 2,
    "lineWidth": 100,
    "lineEnding": "lf"
  },
  "organizeImports": {
    "enabled": true
  },
  "linter": {
    "enabled": true,
    "rules": {
      "recommended": true,
      "suspicious": {
        "noExplicitAny": "warn",
        "noConsoleLog": "off",
        "noControlCharactersInRegex": "off"
      },
      "style": {
        "noNonNullAssertion": "off",
        "useImportType": "warn"
      },
      "correctness": {
        "noUnusedVariables": "warn"
      }
    }
  },
  "javascript": {
    "formatter": {
      "quoteStyle": "single",
      "semicolons": "always",
      "trailingCommas": "all"
    }
  },
  "json": {
    "formatter": {
      "enabled": true
    }
  },
  "overrides": [
    {
      "include": ["**/*.svelte"],
      "linter": {
        "rules": {
          "style": {
            "useConst": "off"
          },
          "correctness": {
            "noUnusedVariables": "off"
          }
        }
      }
    }
  ]
}
